bincache/__init__.py
bincache/cache.py
bincache/cli.py
bincache/config.py
bincache/logger.py
bincache/signature.py
tests/__init__.py
tests/test_cache.py
tests/test_cli.py
tests/test_config.py
tests/test_log.py
tests/test_signature.py
bincache-0.0.16.dist-info/LICENSE
bincache-0.0.16.dist-info/METADATA
bincache-0.0.16.dist-info/WHEEL
bincache-0.0.16.dist-info/entry_points.txt
bincache-0.0.16.dist-info/top_level.txt
bincache-0.0.16.dist-info/RECORD
