Metadata-Version: 2.1
Name: bincache
Version: 0.0.16
Summary: Bincache is a command-line utility designed to cache the output of executable binaries and shell commands.
Home-page: https://github.com/simpx/bincache
Author: simpx
Author-email: simpxx@gmail.com
License: MIT
Classifier: Development Status :: 3 - Alpha
Classifier: Intended Audience :: Developers
Classifier: License :: OSI Approved :: MIT License
Classifier: Programming Language :: Python :: 3
Classifier: Programming Language :: Python :: 3.6
Classifier: Programming Language :: Python :: 3.7
Classifier: Programming Language :: Python :: 3.8
Classifier: Programming Language :: Python :: 3.9
License-File: LICENSE
